AUTHORS
HISTORY.rst
LICENSE
MANIFEST.in
README.rst
setup.py
pointhq/__init__.py
pointhq/api.py
pointhq/base.py
pointhq/exceptions.py
pointhq/helpers.py
pointhq.egg-info/PKG-INFO
pointhq.egg-info/SOURCES.txt
pointhq.egg-info/dependency_links.txt
pointhq.egg-info/requires.txt
pointhq.egg-info/top_level.txt